piwebapiml/__init__.py
piwebapiml/pml_stream.py
piwebapiml/pml_stream_set.py
piwebapiml/pml_web_api_client.py
test/__init__.py
test/test_data.py
pidevguru_piwebapi_ml-1.0.0.dist-info/LICENSE.md
pidevguru_piwebapi_ml-1.0.0.dist-info/METADATA
pidevguru_piwebapi_ml-1.0.0.dist-info/WHEEL
pidevguru_piwebapi_ml-1.0.0.dist-info/top_level.txt
pidevguru_piwebapi_ml-1.0.0.dist-info/RECORD
